README.rst
setup.py
cronsingleton/__init__.py
cronsingleton/script.py
cronsingleton.egg-info/PKG-INFO
cronsingleton.egg-info/SOURCES.txt
cronsingleton.egg-info/dependency_links.txt
cronsingleton.egg-info/entry_points.txt
cronsingleton.egg-info/requires.txt
cronsingleton.egg-info/top_level.txt