Metadata-Version: 1.0
Name: cronsingleton
Version: 1.0
Summary: A user level cron cheduler.
Home-page: http://packages.python.org/cronsingleton
Author: Adam Terrey
Author-email: arterrey@pretaweb.com
License: BSD
Keywords: cron
Platform: UNKNOWN
